power_instruction_analyzer-0.2.0.dist-info/METADATA
power_instruction_analyzer-0.2.0.dist-info/WHEEL
power_instruction_analyzer.cpython-38-x86_64-linux-gnu.so
power_instruction_analyzer-0.2.0.dist-info/RECORD
