Metadata-Version: 2.1
Name: power-instruction-analyzer
Version: 0.2.0
Summary: Program to analyze the behavior of Power ISA instructions
Author: Jacob Lifshay <programmerjake@gmail.com>
Author-Email: Jacob Lifshay <programmerjake@gmail.com>
License: LGPL-2.1-or-later
